tri_event/__init__.py
tri.event-2.1.0.dist-info/AUTHORS.rst
tri.event-2.1.0.dist-info/LICENSE
tri.event-2.1.0.dist-info/METADATA
tri.event-2.1.0.dist-info/WHEEL
tri.event-2.1.0.dist-info/top_level.txt
tri.event-2.1.0.dist-info/RECORD
