Metadata-Version: 2.1
Name: tri.event
Version: 2.1.0
Summary: Client library for TriOptima event bus and related APIs
Home-page: UNKNOWN
Author: TriOptima
Author-email: XYZ@trioptima.com
License: BSD
Keywords: tri.event
Platform: UNKNOWN
Classifier: Development Status :: 5 - Production/Stable
Classifier: Intended Audience :: Developers
Classifier: License :: OSI Approved :: BSD License
Classifier: Natural Language :: English
Classifier: Programming Language :: Python :: 3.6
Requires-Dist: requests (>=2.20.1)
